{
  "id": "https://openalex.org/W4412358114",
  "doi": "https://doi.org/10.3847/1538-4357/addf40",
  "title": "Spectroastrometry and Reverberation Mapping of Active Galactic Nuclei. II. Measuring Geometric Distances and Black Hole Masses of Four Nearby Quasars",
  "display_name": "Spectroastrometry and Reverberation Mapping of Active Galactic Nuclei. II. Measuring Geometric Distances and Black Hole Masses of Four Nearby Quasars",
  "publication_year": 2025,
  "publication_date": "2025-07-11",
  "ids": {
    "openalex": "https://openalex.org/W4412358114",
    "doi": "https://doi.org/10.3847/1538-4357/addf40"
  },
  "language": "en",
  "primary_location": {
    "id": "doi:10.3847/1538-4357/addf40",
    "is_oa": true,
    "landing_page_url": "https://doi.org/10.3847/1538-4357/addf40",
    "pdf_url": null,
    "source": {
      "id": "https://openalex.org/S1980519",
      "display_name": "The Astrophysical Journal",
      "issn_l": "0004-637X",
      "issn": [
        "0004-637X",
        "1538-4357"
      ],
      "is_oa": true,
      "is_in_doaj": true,
      "is_core": true,
      "host_organization": "https://openalex.org/P4310320083",
      "host_organization_name": "IOP Publishing",
      "host_organization_lineage": [
        "https://openalex.org/P4310320083",
        "https://openalex.org/P4310311669"
      ],
      "host_organization_lineage_names": [
        "IOP Publishing",
        "Institute of Physics"
      ],
      "type": "journal"
    },
    "license": "cc-by",
    "license_id": "https://openalex.org/licenses/cc-by",
    "version": "publishedVersion",
    "is_accepted": true,
    "is_published": true,
    "raw_source_name": "The Astrophysical Journal",
    "raw_type": "journal-article"
  },
  "type": "article",
  "indexed_in": [
    "arxiv",
    "crossref",
    "doaj"
  ],
  "open_access": {
    "is_oa": true,
    "oa_status": "gold",
    "oa_url": "https://doi.org/10.3847/1538-4357/addf40",
    "any_repository_has_fulltext": false
  },
  "authorships": [
    {
      "author_position": "first",
      "author": {
        "id": "https://openalex.org/A5107809220",
        "display_name": "Yan-Rong Li",
        "orcid": "https://orcid.org/0000-0001-5841-9179"
      },
      "institutions": [],
      "countries": [],
      "is_corresponding": true,
      "raw_author_name": "Yan-Rong Li",
      "raw_affiliation_strings": [],
      "affiliations": []
    },
    {
      "author_position": "middle",
      "author": {
        "id": "https://openalex.org/A5025276453",
        "display_name": "J. Shangguan",
        "orcid": "https://orcid.org/0000-0002-4569-9009"
      },
      "institutions": [],
      "countries": [],
      "is_corresponding": false,
      "raw_author_name": "Jinyi Shangguan",
      "raw_affiliation_strings": [],
      "affiliations": []
    },
    {
      "author_position": "middle",
      "author": {
        "id": "https://openalex.org/A5004992056",
        "display_name": "Jian\u2010Min Wang",
        "orcid": "https://orcid.org/0000-0001-9449-9268"
      },
      "institutions": [],
      "countries": [],
      "is_corresponding": false,
      "raw_author_name": "Jian-Min Wang",
      "raw_affiliation_strings": [],
      "affiliations": []
    },
    {
      "author_position": "middle",
      "author": {
        "id": "https://openalex.org/A5031606567",
        "display_name": "R. Davies",
        "orcid": "https://orcid.org/0000-0003-4949-7217"
      },
      "institutions": [],
      "countries": [],
      "is_corresponding": false,
      "raw_author_name": "Ric Davies",
      "raw_affiliation_strings": [],
      "affiliations": []
    },
    {
      "author_position": "middle",
      "author": {
        "id": "https://openalex.org/A5003727453",
        "display_name": "D. Santos",
        "orcid": "https://orcid.org/0000-0002-5687-0609"
      },
      "institutions": [],
      "countries": [],
      "is_corresponding": false,
      "raw_author_name": "Daryl J. D. Santos",
      "raw_affiliation_strings": [],
      "affiliations": []
    },
    {
      "author_position": "middle",
      "author": {
        "id": "https://openalex.org/A5111664472",
        "display_name": "Frank Eisenhauer",
        "orcid": null
      },
      "institutions": [],
      "countries": [],
      "is_corresponding": false,
      "raw_author_name": "Frank Eisenhauer",
      "raw_affiliation_strings": [],
      "affiliations": []
    },
    {
      "author_position": "middle",
      "author": {
        "id": "https://openalex.org/A5091094415",
        "display_name": "Yu-Yang Songsheng",
        "orcid": "https://orcid.org/0000-0003-4042-7191"
      },
      "institutions": [],
      "countries": [],
      "is_corresponding": false,
      "raw_author_name": "Yu-Yang Songsheng",
      "raw_affiliation_strings": [],
      "affiliations": []
    },
    {
      "author_position": "middle",
      "author": {
        "id": "https://openalex.org/A5031781401",
        "display_name": "Hartmut Winkler",
        "orcid": "https://orcid.org/0000-0003-2662-0526"
      },
      "institutions": [],
      "countries": [],
      "is_corresponding": false,
      "raw_author_name": "Hartmut Winkler",
      "raw_affiliation_strings": [],
      "affiliations": []
    },
    {
      "author_position": "middle",
      "author": {
        "id": "https://openalex.org/A5035455643",
        "display_name": "J. Aceituno",
        "orcid": "https://orcid.org/0000-0003-0487-1105"
      },
      "institutions": [],
      "countries": [],
      "is_corresponding": false,
      "raw_author_name": "Jes\u00fas Aceituno",
      "raw_affiliation_strings": [],
      "affiliations": []
    },
    {
      "author_position": "middle",
      "author": {
        "id": "https://openalex.org/A5111198821",
        "display_name": "Hua-Rui Bai",
        "orcid": null
      },
      "institutions": [],
      "countries": [],
      "is_corresponding": false,
      "raw_author_name": "Hua-Rui Bai",
      "raw_affiliation_strings": [],
      "affiliations": []
    },
    {
      "author_position": "middle",
      "author": {
        "id": "https://openalex.org/A5112577887",
        "display_name": "Jinming Bai",
        "orcid": null
      },
      "institutions": [],
      "countries": [],
      "is_corresponding": false,
      "raw_author_name": "Jin-Ming Bai",
      "raw_affiliation_strings": [],
      "affiliations": []
    },
    {
      "author_position": "middle",
      "author": {
        "id": "https://openalex.org/A5063140041",
        "display_name": "M. S. Brotherton",
        "orcid": "https://orcid.org/0000-0002-1207-0909"
      },
      "institutions": [],
      "countries": [],
      "is_corresponding": false,
      "raw_author_name": "Michael S. Brotherton",
      "raw_affiliation_strings": [],
      "affiliations": []
    },
    {
      "author_position": "middle",
      "author": {
        "id": "https://openalex.org/A5105034248",
        "display_name": "Yixian Cao",
        "orcid": "https://orcid.org/0000-0001-5301-1326"
      },
      "institutions": [],
      "countries": [],
      "is_corresponding": false,
      "raw_author_name": "Yixian Cao",
      "raw_affiliation_strings": [],
      "affiliations": []
    },
    {
      "author_position": "middle",
      "author": {
        "id": "https://openalex.org/A5100668521",
        "display_name": "Yongjie Chen",
        "orcid": "https://orcid.org/0000-0003-0853-9767"
      },
      "institutions": [],
      "countries": [],
      "is_corresponding": false,
      "raw_author_name": "Yong-Jie Chen",
      "raw_affiliation_strings": [],
      "affiliations": []
    },
    {
      "author_position": "middle",
      "author": {
        "id": "https://openalex.org/A5013496509",
        "display_name": "Pu Du",
        "orcid": "https://orcid.org/0000-0002-5830-3544"
      },
      "institutions": [],
      "countries": [],
      "is_corresponding": false,
      "raw_author_name": "Pu Du",
      "raw_affiliation_strings": [],
      "affiliations": []
    },
    {
      "author_position": "middle",
      "author": {
        "id": "https://openalex.org/A5005388909",
        "display_name": "Feng-Na Fang",
        "orcid": null
      },
      "institutions": [],
      "countries": [],
      "is_corresponding": false,
      "raw_author_name": "Feng-Na Fang",
      "raw_affiliation_strings": [],
      "affiliations": []
    },
    {
      "author_position": "middle",
      "author": {
        "id": "https://openalex.org/A5101609902",
        "display_name": "Jiaqi Feng",
        "orcid": "https://orcid.org/0000-0002-6212-6755"
      },
      "institutions": [],
      "countries": [],
      "is_corresponding": false,
      "raw_author_name": "Jia-Qi Feng",
      "raw_affiliation_strings": [],
      "affiliations": []
    },
    {
      "author_position": "middle",
      "author": {
        "id": "https://openalex.org/A5057771393",
        "display_name": "H. Feuchtgruber",
        "orcid": null
      },
      "institutions": [],
      "countries": [],
      "is_corresponding": false,
      "raw_author_name": "Helmut Feuchtgruber",
      "raw_affiliation_strings": [],
      "affiliations": []
    },
    {
      "author_position": "middle",
      "author": {
        "id": "https://openalex.org/A5091386388",
        "display_name": "N. M. F\u00f6rster Schreiber",
        "orcid": "https://orcid.org/0000-0003-4264-3381"
      },
      "institutions": [],
      "countries": [],
      "is_corresponding": false,
      "raw_author_name": "Natascha M. F\u00f6rster Schreiber",
      "raw_affiliation_strings": [],
      "affiliations": []
    },
    {
      "author_position": "middle",
      "author": {
        "id": "https://openalex.org/A5050316033",
        "display_name": "Yi-Xin Fu",
        "orcid": null
      },
      "institutions": [],
      "countries": [],
      "is_corresponding": false,
      "raw_author_name": "Yi-Xin Fu",
      "raw_affiliation_strings": [],
      "affiliations": []
    },
    {
      "author_position": "middle",
      "author": {
        "id": "https://openalex.org/A5032049136",
        "display_name": "R. Genzel",
        "orcid": "https://orcid.org/0000-0002-2767-9653"
      },
      "institutions": [],
      "countries": [],
      "is_corresponding": false,
      "raw_author_name": "Reinhard Genzel",
      "raw_affiliation_strings": [],
      "affiliations": []
    },
    {
      "author_position": "middle",
      "author": {
        "id": "https://openalex.org/A5070619820",
        "display_name": "S. Gillessen",
        "orcid": "https://orcid.org/0000-0002-5708-0481"
      },
      "institutions": [],
      "countries": [],
      "is_corresponding": false,
      "raw_author_name": "Stefan Gillessen",
      "raw_affiliation_strings": [],
      "affiliations": []
    },
    {
      "author_position": "middle",
      "author": {
        "id": "https://openalex.org/A5054184482",
        "display_name": "Luis C. Ho",
        "orcid": "https://orcid.org/0000-0001-6947-5846"
      },
      "institutions": [],
      "countries": [],
      "is_corresponding": false,
      "raw_author_name": "Luis C. Ho",
      "raw_affiliation_strings": [],
      "affiliations": []
    },
    {
      "author_position": "middle",
      "author": {
        "id": "https://openalex.org/A5100357677",
        "display_name": "Hu Chen",
        "orcid": "https://orcid.org/0000-0001-9300-6572"
      },
      "institutions": [],
      "countries": [],
      "is_corresponding": false,
      "raw_author_name": "Chen Hu",
      "raw_affiliation_strings": [],
      "affiliations": []
    },
    {
      "author_position": "middle",
      "author": {
        "id": "https://openalex.org/A5101948508",
        "display_name": "S. Abdollahi",
        "orcid": "https://orcid.org/0000-0003-3086-7804"
      },
      "institutions": [],
      "countries": [],
      "is_corresponding": false,
      "raw_author_name": "Jun-Rong Liu",
      "raw_affiliation_strings": [],
      "affiliations": []
    },
    {
      "author_position": "middle",
      "author": {
        "id": "https://openalex.org/A5052954301",
        "display_name": "D. Lutz",
        "orcid": "https://orcid.org/0000-0003-0291-9582"
      },
      "institutions": [],
      "countries": [],
      "is_corresponding": false,
      "raw_author_name": "Dieter Lutz",
      "raw_affiliation_strings": [],
      "affiliations": []
    },
    {
      "author_position": "middle",
      "author": {
        "id": "https://openalex.org/A5090479752",
        "display_name": "Thomas Ott",
        "orcid": "https://orcid.org/0000-0003-1572-0396"
      },
      "institutions": [],
      "countries": [],
      "is_corresponding": false,
      "raw_author_name": "Thomas Ott",
      "raw_affiliation_strings": [],
      "affiliations": []
    },
    {
      "author_position": "middle",
      "author": {
        "id": "https://openalex.org/A5055323394",
        "display_name": "R. Petrov",
        "orcid": "https://orcid.org/0000-0003-4759-6051"
      },
      "institutions": [],
      "countries": [],
      "is_corresponding": false,
      "raw_author_name": "Romain G. Petrov",
      "raw_affiliation_strings": [],
      "affiliations": []
    },
    {
      "author_position": "middle",
      "author": {
        "id": "https://openalex.org/A5110723296",
        "display_name": "S. Rabien",
        "orcid": null
      },
      "institutions": [],
      "countries": [],
      "is_corresponding": false,
      "raw_author_name": "Sebastian Rabien",
      "raw_affiliation_strings": [],
      "affiliations": []
    },
    {
      "author_position": "middle",
      "author": {
        "id": "https://openalex.org/A5058052563",
        "display_name": "Thomas Shimizu",
        "orcid": "https://orcid.org/0000-0002-2125-4670"
      },
      "institutions": [],
      "countries": [],
      "is_corresponding": false,
      "raw_author_name": "Taro Shimizu",
      "raw_affiliation_strings": [],
      "affiliations": []
    },
    {
      "author_position": "middle",
      "author": {
        "id": "https://openalex.org/A5054387556",
        "display_name": "E. Sturm",
        "orcid": "https://orcid.org/0000-0002-0018-3666"
      },
      "institutions": [],
      "countries": [],
      "is_corresponding": false,
      "raw_author_name": "Eckhard Sturm",
      "raw_affiliation_strings": [],
      "affiliations": []
    },
    {
      "author_position": "middle",
      "author": {
        "id": "https://openalex.org/A5087379508",
        "display_name": "L. J. Tacconi",
        "orcid": "https://orcid.org/0000-0002-1485-9401"
      },
      "institutions": [],
      "countries": [],
      "is_corresponding": false,
      "raw_author_name": "Linda J. Tacconi",
      "raw_affiliation_strings": [],
      "affiliations": []
    },
    {
      "author_position": "middle",
      "author": {
        "id": "https://openalex.org/A5084903015",
        "display_name": "Yilin Wang",
        "orcid": "https://orcid.org/0000-0002-3386-5380"
      },
      "institutions": [],
      "countries": [],
      "is_corresponding": false,
      "raw_author_name": "Yi-Lin Wang",
      "raw_affiliation_strings": [],
      "affiliations": []
    },
    {
      "author_position": "middle",
      "author": {
        "id": "https://openalex.org/A5045713406",
        "display_name": "Zhu-Heng Yao",
        "orcid": "https://orcid.org/0009-0000-1228-2373"
      },
      "institutions": [],
      "countries": [],
      "is_corresponding": false,
      "raw_author_name": "Zhu-Heng Yao",
      "raw_affiliation_strings": [],
      "affiliations": []
    },
    {
      "author_position": "middle",
      "author": {
        "id": "https://openalex.org/A5108918386",
        "display_name": "Shuo Zhai",
        "orcid": null
      },
      "institutions": [],
      "countries": [],
      "is_corresponding": false,
      "raw_author_name": "Shuo Zhai",
      "raw_affiliation_strings": [],
      "affiliations": []
    },
    {
      "author_position": "middle",
      "author": {
        "id": "https://openalex.org/A5092060744",
        "display_name": "Hao Zhang",
        "orcid": "https://orcid.org/0000-0002-5595-0447"
      },
      "institutions": [],
      "countries": [],
      "is_corresponding": false,
      "raw_author_name": "Hao Zhang",
      "raw_affiliation_strings": [],
      "affiliations": []
    },
    {
      "author_position": "middle",
      "author": {
        "id": "https://openalex.org/A5021199407",
        "display_name": "Yipeng Zhao",
        "orcid": "https://orcid.org/0009-0005-4583-6818"
      },
      "institutions": [],
      "countries": [],
      "is_corresponding": false,
      "raw_author_name": "Yi-Peng Zhao",
      "raw_affiliation_strings": [],
      "affiliations": []
    },
    {
      "author_position": "last",
      "author": {
        "id": "https://openalex.org/A5113985920",
        "display_name": "Yu Zhao",
        "orcid": "https://orcid.org/0009-0001-4295-8562"
      },
      "institutions": [],
      "countries": [],
      "is_corresponding": false,
      "raw_author_name": "Yu Zhao",
      "raw_affiliation_strings": [],
      "affiliations": []
    }
  ],
  "institutions": [],
  "countries_distinct_count": 0,
  "institutions_distinct_count": 38,
  "corresponding_author_ids": [
    "https://openalex.org/A5107809220"
  ],
  "corresponding_institution_ids": [],
  "apc_list": {
    "value": 4499,
    "currency": "USD",
    "value_usd": 4499
  },
  "apc_paid": {
    "value": 4499,
    "currency": "USD",
    "value_usd": 4499
  },
  "fwci": 9.83597141,
  "has_fulltext": false,
  "cited_by_count": 3,
  "citation_normalized_percentile": {
    "value": 0.94684097,
    "is_in_top_1_percent": false,
    "is_in_top_10_percent": true
  },
  "cited_by_percentile_year": {
    "min": 96,
    "max": 97
  },
  "biblio": {
    "volume": "988",
    "issue": "1",
    "first_page": "42",
    "last_page": "42"
  },
  "is_retracted": false,
  "is_paratext": false,
  "is_xpac": false,
  "primary_topic": {
    "id": "https://openalex.org/T10026",
    "display_name": "Galaxies: Formation, Evolution, Phenomena",
    "score": 0.9998000264167786,
    "subfield": {
      "id": "https://openalex.org/subfields/3103",
      "display_name": "Astronomy and Astrophysics"
    },
    "field": {
      "id": "https://openalex.org/fields/31",
      "display_name": "Physics and Astronomy"
    },
    "domain": {
      "id": "https://openalex.org/domains/3",
      "display_name": "Physical Sciences"
    }
  },
  "topics": [
    {
      "id": "https://openalex.org/T10026",
      "display_name": "Galaxies: Formation, Evolution, Phenomena",
      "score": 0.9998000264167786,
      "subfield": {
        "id": "https://openalex.org/subfields/3103",
        "display_name": "Astronomy and Astrophysics"
      },
      "field": {
        "id": "https://openalex.org/fields/31",
        "display_name": "Physics and Astronomy"
      },
      "domain": {
        "id": "https://openalex.org/domains/3",
        "display_name": "Physical Sciences"
      }
    },
    {
      "id": "https://openalex.org/T10039",
      "display_name": "Stellar, planetary, and galactic studies",
      "score": 0.9991999864578247,
      "subfield": {
        "id": "https://openalex.org/subfields/3103",
        "display_name": "Astronomy and Astrophysics"
      },
      "field": {
        "id": "https://openalex.org/fields/31",
        "display_name": "Physics and Astronomy"
      },
      "domain": {
        "id": "https://openalex.org/domains/3",
        "display_name": "Physical Sciences"
      }
    },
    {
      "id": "https://openalex.org/T10744",
      "display_name": "Astrophysical Phenomena and Observations",
      "score": 0.9988999962806702,
      "subfield": {
        "id": "https://openalex.org/subfields/3103",
        "display_name": "Astronomy and Astrophysics"
      },
      "field": {
        "id": "https://openalex.org/fields/31",
        "display_name": "Physics and Astronomy"
      },
      "domain": {
        "id": "https://openalex.org/domains/3",
        "display_name": "Physical Sciences"
      }
    }
  ],
  "keywords": [
    {
      "id": "https://openalex.org/keywords/physics",
      "display_name": "Physics",
      "score": 0.969882607460022
    },
    {
      "id": "https://openalex.org/keywords/quasar",
      "display_name": "Quasar",
      "score": 0.8945410251617432
    },
    {
      "id": "https://openalex.org/keywords/reverberation-mapping",
      "display_name": "Reverberation mapping",
      "score": 0.7253307104110718
    },
    {
      "id": "https://openalex.org/keywords/active-galactic-nucleus",
      "display_name": "Active galactic nucleus",
      "score": 0.717547595500946
    },
    {
      "id": "https://openalex.org/keywords/astrophysics",
      "display_name": "Astrophysics",
      "score": 0.6468391418457031
    },
    {
      "id": "https://openalex.org/keywords/black-hole",
      "display_name": "Black hole (networking)",
      "score": 0.5464918613433838
    },
    {
      "id": "https://openalex.org/keywords/supermassive-black-hole",
      "display_name": "Supermassive black hole",
      "score": 0.4739660918712616
    },
    {
      "id": "https://openalex.org/keywords/astronomy",
      "display_name": "Astronomy",
      "score": 0.45905861258506775
    },
    {
      "id": "https://openalex.org/keywords/reverberation",
      "display_name": "Reverberation",
      "score": 0.4578082263469696
    },
    {
      "id": "https://openalex.org/keywords/intermediate-mass-black-hole",
      "display_name": "Intermediate-mass black hole",
      "score": 0.4211651384830475
    },
    {
      "id": "https://openalex.org/keywords/galaxy",
      "display_name": "Galaxy",
      "score": 0.3092558979988098
    }
  ],
  "concepts": [
    {
      "id": "https://openalex.org/C121332964",
      "wikidata": "https://www.wikidata.org/wiki/Q413",
      "display_name": "Physics",
      "level": 0,
      "score": 0.969882607460022
    },
    {
      "id": "https://openalex.org/C135041427",
      "wikidata": "https://www.wikidata.org/wiki/Q83373",
      "display_name": "Quasar",
      "level": 3,
      "score": 0.8945410251617432
    },
    {
      "id": "https://openalex.org/C48841040",
      "wikidata": "https://www.wikidata.org/wiki/Q3780420",
      "display_name": "Reverberation mapping",
      "level": 4,
      "score": 0.7253307104110718
    },
    {
      "id": "https://openalex.org/C43481613",
      "wikidata": "https://www.wikidata.org/wiki/Q46587",
      "display_name": "Active galactic nucleus",
      "level": 3,
      "score": 0.717547595500946
    },
    {
      "id": "https://openalex.org/C44870925",
      "wikidata": "https://www.wikidata.org/wiki/Q37547",
      "display_name": "Astrophysics",
      "level": 1,
      "score": 0.6468391418457031
    },
    {
      "id": "https://openalex.org/C50341732",
      "wikidata": "https://www.wikidata.org/wiki/Q880302",
      "display_name": "Black hole (networking)",
      "level": 5,
      "score": 0.5464918613433838
    },
    {
      "id": "https://openalex.org/C173120059",
      "wikidata": "https://www.wikidata.org/wiki/Q40392",
      "display_name": "Supermassive black hole",
      "level": 3,
      "score": 0.4739660918712616
    },
    {
      "id": "https://openalex.org/C1276947",
      "wikidata": "https://www.wikidata.org/wiki/Q333",
      "display_name": "Astronomy",
      "level": 1,
      "score": 0.45905861258506775
    },
    {
      "id": "https://openalex.org/C95851461",
      "wikidata": "https://www.wikidata.org/wiki/Q468809",
      "display_name": "Reverberation",
      "level": 2,
      "score": 0.4578082263469696
    },
    {
      "id": "https://openalex.org/C18609725",
      "wikidata": "https://www.wikidata.org/wiki/Q1050633",
      "display_name": "Intermediate-mass black hole",
      "level": 4,
      "score": 0.4211651384830475
    },
    {
      "id": "https://openalex.org/C98444146",
      "wikidata": "https://www.wikidata.org/wiki/Q318",
      "display_name": "Galaxy",
      "level": 2,
      "score": 0.3092558979988098
    },
    {
      "id": "https://openalex.org/C74172769",
      "wikidata": "https://www.wikidata.org/wiki/Q1446839",
      "display_name": "Routing (electronic design automation)",
      "level": 2,
      "score": 0.0
    },
    {
      "id": "https://openalex.org/C31258907",
      "wikidata": "https://www.wikidata.org/wiki/Q1301371",
      "display_name": "Computer network",
      "level": 1,
      "score": 0.0
    },
    {
      "id": "https://openalex.org/C41008148",
      "wikidata": "https://www.wikidata.org/wiki/Q21198",
      "display_name": "Computer science",
      "level": 0,
      "score": 0.0
    },
    {
      "id": "https://openalex.org/C104954878",
      "wikidata": "https://www.wikidata.org/wiki/Q1648707",
      "display_name": "Routing protocol",
      "level": 3,
      "score": 0.0
    },
    {
      "id": "https://openalex.org/C89305328",
      "wikidata": "https://www.wikidata.org/wiki/Q1755411",
      "display_name": "Link-state routing protocol",
      "level": 4,
      "score": 0.0
    },
    {
      "id": "https://openalex.org/C24890656",
      "wikidata": "https://www.wikidata.org/wiki/Q82811",
      "display_name": "Acoustics",
      "level": 1,
      "score": 0.0
    }
  ],
  "mesh": [],
  "locations_count": 4,
  "locations": [
    {
      "id": "doi:10.3847/1538-4357/addf40",
      "is_oa": true,
      "landing_page_url": "https://doi.org/10.3847/1538-4357/addf40",
      "pdf_url": null,
      "source": {
        "id": "https://openalex.org/S1980519",
        "display_name": "The Astrophysical Journal",
        "issn_l": "0004-637X",
        "issn": [
          "0004-637X",
          "1538-4357"
        ],
        "is_oa": true,
        "is_in_doaj": true,
        "is_core": true,
        "host_organization": "https://openalex.org/P4310320083",
        "host_organization_name": "IOP Publishing",
        "host_organization_lineage": [
          "https://openalex.org/P4310320083",
          "https://openalex.org/P4310311669"
        ],
        "host_organization_lineage_names": [
          "IOP Publishing",
          "Institute of Physics"
        ],
        "type": "journal"
      },
      "license": "cc-by",
      "license_id": "https://openalex.org/licenses/cc-by",
      "version": "publishedVersion",
      "is_accepted": true,
      "is_published": true,
      "raw_source_name": "The Astrophysical Journal",
      "raw_type": "journal-article"
    },
    {
      "id": "pmh:oai:arXiv.org:2502.18856",
      "is_oa": true,
      "landing_page_url": "http://arxiv.org/abs/2502.18856",
      "pdf_url": "https://arxiv.org/pdf/2502.18856",
      "source": {
        "id": "https://openalex.org/S4306400194",
        "display_name": "arXiv (Cornell University)",
        "issn_l": null,
        "issn": null,
        "is_oa": true,
        "is_in_doaj": false,
        "is_core": false,
        "host_organization": "https://openalex.org/I205783295",
        "host_organization_name": "Cornell University",
        "host_organization_lineage": [
          "https://openalex.org/I205783295"
        ],
        "host_organization_lineage_names": [],
        "type": "repository"
      },
      "license": null,
      "license_id": null,
      "version": "submittedVersion",
      "is_accepted": false,
      "is_published": false,
      "raw_source_name": null,
      "raw_type": "text"
    },
    {
      "id": "pmh:oai:digital.csic.es:10261/398587",
      "is_oa": true,
      "landing_page_url": "http://hdl.handle.net/10261/398587",
      "pdf_url": null,
      "source": {
        "id": "https://openalex.org/S4306400616",
        "display_name": "DIGITAL.CSIC (Spanish National Research Council (CSIC))",
        "issn_l": null,
        "issn": null,
        "is_oa": false,
        "is_in_doaj": false,
        "is_core": false,
        "host_organization": "https://openalex.org/I134820265",
        "host_organization_name": "Consejo Superior de Investigaciones Cient\u00edficas",
        "host_organization_lineage": [
          "https://openalex.org/I134820265"
        ],
        "host_organization_lineage_names": [],
        "type": "repository"
      },
      "license": "cc-by",
      "license_id": "https://openalex.org/licenses/cc-by",
      "version": "submittedVersion",
      "is_accepted": false,
      "is_published": false,
      "raw_source_name": null,
      "raw_type": "info:eu-repo/semantics/publishedVersion"
    },
    {
      "id": "pmh:oai:doaj.org/article:f5019cdbccf04036af628a35d56636c7",
      "is_oa": true,
      "landing_page_url": "https://doaj.org/article/f5019cdbccf04036af628a35d56636c7",
      "pdf_url": null,
      "source": {
        "id": "https://openalex.org/S4306401280",
        "display_name": "DOAJ (DOAJ: Directory of Open Access Journals)",
        "issn_l": null,
        "issn": null,
        "is_oa": false,
        "is_in_doaj": false,
        "is_core": false,
        "host_organization": null,
        "host_organization_name": null,
        "host_organization_lineage": [],
        "host_organization_lineage_names": [],
        "type": "repository"
      },
      "license": "cc-by-sa",
      "license_id": "https://openalex.org/licenses/cc-by-sa",
      "version": "submittedVersion",
      "is_accepted": false,
      "is_published": false,
      "raw_source_name": "The Astrophysical Journal, Vol 988, Iss 1, p 42 (2025)",
      "raw_type": "article"
    }
  ],
  "best_oa_location": {
    "id": "doi:10.3847/1538-4357/addf40",
    "is_oa": true,
    "landing_page_url": "https://doi.org/10.3847/1538-4357/addf40",
    "pdf_url": null,
    "source": {
      "id": "https://openalex.org/S1980519",
      "display_name": "The Astrophysical Journal",
      "issn_l": "0004-637X",
      "issn": [
        "0004-637X",
        "1538-4357"
      ],
      "is_oa": true,
      "is_in_doaj": true,
      "is_core": true,
      "host_organization": "https://openalex.org/P4310320083",
      "host_organization_name": "IOP Publishing",
      "host_organization_lineage": [
        "https://openalex.org/P4310320083",
        "https://openalex.org/P4310311669"
      ],
      "host_organization_lineage_names": [
        "IOP Publishing",
        "Institute of Physics"
      ],
      "type": "journal"
    },
    "license": "cc-by",
    "license_id": "https://openalex.org/licenses/cc-by",
    "version": "publishedVersion",
    "is_accepted": true,
    "is_published": true,
    "raw_source_name": "The Astrophysical Journal",
    "raw_type": "journal-article"
  },
  "sustainable_development_goals": [],
  "awards": [
    {
      "id": "https://openalex.org/G8316754040",
      "display_name": null,
      "funder_award_id": "11991050",
      "funder_id": "https://openalex.org/F4320321001",
      "funder_display_name": "National Natural Science Foundation of China"
    }
  ],
  "funders": [
    {
      "id": "https://openalex.org/F4320321001",
      "display_name": "National Natural Science Foundation of China",
      "ror": "https://ror.org/01h0zpd94"
    }
  ],
  "has_content": {
    "grobid_xml": false,
    "pdf": false
  },
  "referenced_works_count": 83,
  "referenced_works": [
    "https://openalex.org/W4391310374",
    "https://openalex.org/W2124219338",
    "https://openalex.org/W2888532099",
    "https://openalex.org/W2009819793",
    "https://openalex.org/W2041458058",
    "https://openalex.org/W2038207393",
    "https://openalex.org/W3088453165",
    "https://openalex.org/W2031582484",
    "https://openalex.org/W2095424371",
    "https://openalex.org/W2005501750",
    "https://openalex.org/W2963994917",
    "https://openalex.org/W3160011729",
    "https://openalex.org/W4315433646",
    "https://openalex.org/W2131673051",
    "https://openalex.org/W2039024759",
    "https://openalex.org/W2028501147",
    "https://openalex.org/W2972661508",
    "https://openalex.org/W1976965231",
    "https://openalex.org/W2767848202",
    "https://openalex.org/W2085196473",
    "https://openalex.org/W2084087210",
    "https://openalex.org/W2267253354",
    "https://openalex.org/W2082396670",
    "https://openalex.org/W2911890654",
    "https://openalex.org/W2612686510",
    "https://openalex.org/W4283373909",
    "https://openalex.org/W3087603962",
    "https://openalex.org/W3126866012",
    "https://openalex.org/W3190254464",
    "https://openalex.org/W4391223217",
    "https://openalex.org/W2903161739",
    "https://openalex.org/W2162390264",
    "https://openalex.org/W2162283787",
    "https://openalex.org/W2721327568",
    "https://openalex.org/W1990961783",
    "https://openalex.org/W2124811735",
    "https://openalex.org/W4301629510",
    "https://openalex.org/W6931513894",
    "https://openalex.org/W6967506188",
    "https://openalex.org/W6892484129",
    "https://openalex.org/W4403193868",
    "https://openalex.org/W2900683429",
    "https://openalex.org/W4318718483",
    "https://openalex.org/W4406711591",
    "https://openalex.org/W2002610478",
    "https://openalex.org/W2081954377",
    "https://openalex.org/W4220809820",
    "https://openalex.org/W2973130673",
    "https://openalex.org/W1968633967",
    "https://openalex.org/W4288079944",
    "https://openalex.org/W2089750221",
    "https://openalex.org/W2136076204",
    "https://openalex.org/W4399727007",
    "https://openalex.org/W2045953376",
    "https://openalex.org/W2967392395",
    "https://openalex.org/W2995863449",
    "https://openalex.org/W1994576009",
    "https://openalex.org/W2950529756",
    "https://openalex.org/W3135200636",
    "https://openalex.org/W1983954444",
    "https://openalex.org/W2169030850",
    "https://openalex.org/W2998953706",
    "https://openalex.org/W4405883860",
    "https://openalex.org/W3042241317",
    "https://openalex.org/W3159310330",
    "https://openalex.org/W2899680843",
    "https://openalex.org/W3091168073",
    "https://openalex.org/W3102589256",
    "https://openalex.org/W3104977741",
    "https://openalex.org/W3133098730",
    "https://openalex.org/W3105970088",
    "https://openalex.org/W3102230680",
    "https://openalex.org/W3154904408",
    "https://openalex.org/W3101791736",
    "https://openalex.org/W3124690141",
    "https://openalex.org/W3103840038",
    "https://openalex.org/W3098107774",
    "https://openalex.org/W3104494476",
    "https://openalex.org/W3163198113",
    "https://openalex.org/W3105934001",
    "https://openalex.org/W3173731393",
    "https://openalex.org/W3119582496",
    "https://openalex.org/W3103938710"
  ],
  "related_works": [
    "https://openalex.org/W3133858257",
    "https://openalex.org/W2906623658",
    "https://openalex.org/W3104807960",
    "https://openalex.org/W1654612645",
    "https://openalex.org/W3098515426",
    "https://openalex.org/W3098831504",
    "https://openalex.org/W1991074096",
    "https://openalex.org/W4205856556",
    "https://openalex.org/W2025335970",
    "https://openalex.org/W2087652445"
  ],
  "abstract_inverted_index": {
    "Abstract": [
      0
    ],
    "The": [
      1
    ],
    "geometric": [
      2,
      42
    ],
    "distances": [
      3,
      135
    ],
    "of": [
      4,
      14,
      25,
      31,
      44,
      68,
      109,
      121,
      136,
      147,
      213,
      233,
      240,
      253,
      280
    ],
    "active": [
      5
    ],
    "galactic": [
      6
    ],
    "nuclei": [
      7
    ],
    "(AGNs)": [
      8
    ],
    "are": [
      9,
      86,
      96,
      235,
      257
    ],
    "challenging": [
      10
    ],
    "to": [
      11,
      39,
      53,
      114,
      225,
      267
    ],
    "measure": [
      12
    ],
    "because": [
      13
    ],
    "their": [
      15
    ],
    "exceptionally": [
      16
    ],
    "compact": [
      17
    ],
    "structure,": [
      18
    ],
    "yet": [
      19
    ],
    "vast": [
      20
    ],
    "cosmic": [
      21
    ],
    "distances.": [
      22
    ],
    "A": [
      23
    ],
    "combination": [
      24
    ],
    "spectroastrometry": [
      26,
      125
    ],
    "and": [
      27,
      78,
      92,
      126,
      278
    ],
    "reverberation": [
      28,
      130
    ],
    "mapping": [
      29
    ],
    "(SARM)": [
      30
    ],
    "broad-line": [
      32
    ],
    "regions": [
      33
    ],
    "(BLRs)": [
      34
    ],
    "constitutes": [
      35,
      206
    ],
    "a": [
      36,
      144,
      207,
      211,
      226,
      230
    ],
    "novel": [
      37
    ],
    "means": [
      38
    ],
    "probe": [
      40
    ],
    "the": [
      41,
      58,
      83,
      89,
      93,
      106,
      118,
      122,
      137,
      221,
      238,
      243,
      249,
      254,
      261,
      272,
      281
    ],
    "distance": [
      43
    ],
    "AGNs,": [
      45
    ],
    "which": [
      46,
      141
    ],
    "has": [
      47
    ],
    "recently": [
      48
    ],
    "become": [
      49
    ],
    "practically": [
      50
    ],
    "feasible": [
      51
    ],
    "owing": [
      52
    ],
    "successful": [
      54
    ],
    "interferometric": [
      55
    ],
    "observations": [
      56
    ],
    "with": [
      57,
      260,
      271
    ],
    "Very": [
      59
    ],
    "Large": [
      60
    ],
    "Telescope": [
      61
    ],
    "Interferometer/GRAVITY.": [
      62
    ],
    "Here,": [
      63
    ],
    "we": [
      64,
      142
    ],
    "perform": [
      65
    ],
    "SARM": [
      66,
      247
    ],
    "analysis": [
      67
    ],
    "four": [
      69,
      138,
      255
    ],
    "nearby": [
      70
    ],
    "quasars:": [
      71
    ],
    "Mrk": [
      72
    ],
    "509,": [
      73
    ],
    "PDS": [
      74
    ],
    "456,": [
      75
    ],
    "3C": [
      76
    ],
    "273,": [
      77
    ],
    "NGC": [
      79
    ],
    "3783.": [
      80
    ],
    "Results": [
      81
    ],
    "for": [
      82,
      88,
      117,
      210
    ],
    "former": [
      84
    ],
    "two": [
      85,
      95
    ],
    "reported": [
      87
    ],
    "first": [
      90
    ],
    "time,": [
      91
    ],
    "latter": [
      94
    ],
    "revisited": [
      97
    ],
    "using": [
      98
    ],
    "our": [
      99
    ],
    "improved": [
      100
    ],
    "BLR": [
      101,
      123
    ],
    "dynamical": [
      102
    ],
    "modeling": [
      103
    ],
    "that": [
      104,
      220
    ],
    "includes": [
      105
    ],
    "radial-dependent": [
      107
    ],
    "responsivity": [
      108,
      127
    ],
    "BLRs.": [
      110
    ],
    "This": [
      111
    ],
    "allows": [
      112
    ],
    "us": [
      113
    ],
    "self-consistently": [
      115
    ],
    "account": [
      116
    ],
    "emissivity": [
      119
    ],
    "weighting": [
      120,
      128
    ],
    "in": [
      124,
      129,
      242
    ],
    "mapping.": [
      131
    ],
    "We": [
      132
    ],
    "obtain": [
      133
    ],
    "angular-diameter": [
      134
    ],
    "quasars,": [
      139
    ],
    "from": [
      140,
      265
    ],
    "derive": [
      143
    ],
    "Hubble": [
      145
    ],
    "constant": [
      146
    ],
    "<mml:math": [
      148
    ],
    "xmlns:mml=\"http://www.w3.org/1998/Math/MathML\"": [
      149
    ],
    "overflow=\"scroll\">": [
      150
    ],
    "<mml:msub>": [
      151
    ],
    "<mml:mrow>": [
      152,
      155,
      162,
      165,
      169,
      181,
      185,
      193,
      197
    ],
    "<mml:mi>H</mml:mi>": [
      153
    ],
    "</mml:mrow>": [
      154,
      157,
      164,
      168,
      172,
      184,
      188,
      196,
      200
    ],
    "<mml:mn>0</mml:mn>": [
      156
    ],
    "</mml:msub>": [
      158
    ],
    "<mml:mo>=</mml:mo>": [
      159
    ],
    "<mml:mn>6</mml:mn>": [
      160
    ],
    "<mml:msubsup>": [
      161
    ],
    "<mml:mn>9</mml:mn>": [
      163
    ],
    "<mml:mo>\u2212</mml:mo>": [
      166,
      186,
      198
    ],
    "<mml:mn>10</mml:mn>": [
      167
    ],
    "<mml:mo>+</mml:mo>": [
      170
    ],
    "<mml:mn>12</mml:mn>": [
      171
    ],
    "</mml:msubsup>": [
      173
    ],
    "<mml:mspace": [
      174,
      178,
      190
    ],
    "width=\"0.25em\"/>": [
      175,
      179,
      191
    ],
    "<mml:mi": [
      176,
      182,
      194
    ],
    "mathvariant=\"normal\">km</mml:mi>": [
      177
    ],
    "<mml:msup>": [
      180,
      192
    ],
    "mathvariant=\"normal\">s</mml:mi>": [
      183
    ],
    "<mml:mn>1</mml:mn>": [
      187,
      199
    ],
    "</mml:msup>": [
      189,
      201
    ],
    "mathvariant=\"normal\">Mpc</mml:mi>": [
      195
    ],
    "</mml:math>": [
      202
    ],
    ".": [
      203
    ],
    "Although": [
      204
    ],
    "this": [
      205
    ],
    "large": [
      208
    ],
    "uncertainty": [
      209,
      263
    ],
    "measurement": [
      212
    ],
    "H": [
      214
    ],
    "0": [
      215
    ],
    ",": [
      216
    ],
    "it": [
      217
    ],
    "is": [
      218
    ],
    "anticipated": [
      219
    ],
    "precision": [
      222
    ],
    "will": [
      223
    ],
    "improve": [
      224
    ],
    "competitive": [
      227
    ],
    "level": [
      228
    ],
    "once": [
      229
    ],
    "greater": [
      231
    ],
    "number": [
      232
    ],
    "AGNs": [
      234
    ],
    "accessible": [
      236
    ],
    "following": [
      237
    ],
    "upgrade": [
      239
    ],
    "GRAVITY": [
      241
    ],
    "near": [
      244
    ],
    "future.": [
      245
    ],
    "From": [
      246
    ],
    "analysis,": [
      248
    ],
    "black": [
      250,
      275
    ],
    "hole": [
      251,
      276
    ],
    "masses": [
      252,
      277
    ],
    "quasars": [
      256
    ],
    "also": [
      258
    ],
    "measured": [
      259
    ],
    "statistical": [
      262
    ],
    "ranging": [
      264
    ],
    "0.06": [
      266
    ],
    "0.23": [
      268
    ],
    "dex,": [
      269
    ],
    "consistent": [
      270
    ],
    "correlations": [
      273
    ],
    "between": [
      274
    ],
    "properties": [
      279
    ],
    "host": [
      282
    ],
    "bulges.": [
      283
    ]
  },
  "counts_by_year": [
    {
      "year": 2025,
      "cited_by_count": 3
    }
  ],
  "updated_date": "2026-01-13T01:12:25.745995",
  "created_date": "2025-10-10T00:00:00"
}